{
  "data": {
    "tahun": 2022,
    "dpp": "toba",
    "usia": [
      {
        "usia": "17-25",
        "jumlah": 371
      },
      {
        "usia": "26-45",
        "jumlah": 827
      },
      {
        "usia": "45-65",
        "jumlah": 445
      },
      {
        "usia": ">65",
        "jumlah": 75
      }
    ],
    "pendidikan": [
      {
        "pendidikan": "Tidak Tamat SD",
        "jumlah": 26
      },
      {
        "pendidikan": "SD",
        "jumlah": 137
      },
      {
        "pendidikan": "SMP",
        "jumlah": 239
      },
      {
        "pendidikan": "SMA/ SMK",
        "jumlah": 963
      },
      {
        "pendidikan": "D1/ D2/ D3",
        "jumlah": 93
      },
      {
        "pendidikan": "S1/ S2",
        "jumlah": 238
      }
    ]
  }
} 